[
  {
    "word": "plane",
    "phonetic": "/pleɪn/",
    "part_of_speech": "noun",
    "cefr_level": "A1",
    "category": "Transportation",
    "subcategory": "Air",
    "article": "a",
    "plural_form": "planes",
    "countability": "C",
    "regional_variant": "Both",
    "frequency_rank": 1,
    "primary_meaning": "a vehicle that flies in the sky",
    "secondary_meaning": "",
    "usage_notes": "Used for traveling long distances quickly",
    "common_collocations": "fly by plane, plane ticket, plane crash",
    "synonyms": "airplane, aircraft",
    "antonyms": "",
    "image_search_query": "white airplane flying in blue sky",
    "image_context": "A large white passenger plane flying through a bright blue sky with white clouds",
    "image_tags": "plane,airplane,sky,fly,clouds",
    "example_1": "I want to fly by plane.",
    "example_1_translation": "Eu quero voar de avião.",
    "example_2": "The plane is very big.",
    "example_2_translation": "O avião é muito grande.",
    "example_3": "We board the plane at noon.",
    "example_3_translation": "Embarcamos no avião ao meio-dia.",
    "pronunciation_tips": "Rhymes with 'rain' and 'main'",
    "memory_hook": "Planes 'plane' through the sky smoothly",
    "related_words": "fly, airport, travel, sky",
    "common_mistakes": "'Plane' not 'plain' - a plane flies",
    "learning_priority": "high"
  },
  {
    "word": "boat",
    "phonetic": "/bəʊt/",
    "part_of_speech": "noun",
    "cefr_level": "A1",
    "category": "Transportation",
    "subcategory": "Water",
    "article": "a",
    "plural_form": "boats",
    "countability": "C",
    "regional_variant": "Both",
    "frequency_rank": 2,
    "primary_meaning": "a small vehicle that moves on water",
    "secondary_meaning": "",
    "usage_notes": "Smaller than a ship",
    "common_collocations": "row a boat, boat trip, sail boat",
    "synonyms": "ship, vessel",
    "antonyms": "",
    "image_search_query": "small wooden boat on calm lake",
    "image_context": "A small wooden rowboat floating on a calm blue lake with mountains in the background",
    "image_tags": "boat,water,lake,rowboat,sailing",
    "example_1": "We row the boat across the lake.",
    "example_1_translation": "Remamos o barco através do lago.",
    "example_2": "The boat is small.",
    "example_2_translation": "O barco é pequeno.",
    "example_3": "I like to ride in a boat.",
    "example_3_translation": "Eu gosto de andar de barco.",
    "pronunciation_tips": "'Boat' rhymes with 'coat' - long 'o' sound",
    "memory_hook": "You 'boat' across the water",
    "related_words": "water, river, sea, swim",
    "common_mistakes": "'Boat' not 'bote' - has 'a'",
    "learning_priority": "high"
  },
  {
    "word": "taxi",
    "phonetic": "/ˈtæk.si/",
    "part_of_speech": "noun",
    "cefr_level": "A1",
    "category": "Transportation",
    "subcategory": "Road",
    "article": "a",
    "plural_form": "taxis",
    "countability": "C",
    "regional_variant": "Both",
    "frequency_rank": 3,
    "primary_meaning": "a car that you pay to travel in",
    "secondary_meaning": "",
    "usage_notes": "Also called 'cab' in some countries",
    "common_collocations": "take a taxi, call a taxi, taxi driver",
    "synonyms": "cab",
    "antonyms": "",
    "image_search_query": "yellow taxi cab driving on city street",
    "image_context": "A bright yellow taxi cab driving down a busy city street with its sign lit up",
    "image_tags": "taxi,cab,yellow,car,city",
    "example_1": "Let's take a taxi to the airport.",
    "example_1_translation": "Vamos pegar um táxi para o aeroporto.",
    "example_2": "The taxi is waiting outside.",
    "example_2_translation": "O táxi está esperando lá fora.",
    "example_3": "I called a taxi this morning.",
    "example_3_translation": "Eu chamei um táxi esta manhã.",
    "pronunciation_tips": "'Tax-i' - two syllables, short 'a' sound",
    "memory_hook": "You pay a 'tax' for the taxi ride",
    "related_words": "car, bus, drive, city",
    "common_mistakes": "'Taxi' not 'taxy' - spelling matches pronunciation",
    "learning_priority": "high"
  },
  {
    "word": "map",
    "phonetic": "/mæp/",
    "part_of_speech": "noun",
    "cefr_level": "A1",
    "category": "Places",
    "subcategory": "Geography",
    "article": "a",
    "plural_form": "maps",
    "countability": "C",
    "regional_variant": "Both",
    "frequency_rank": 4,
    "primary_meaning": "a picture showing where places are",
    "secondary_meaning": "",
    "usage_notes": "Used for finding your way",
    "common_collocations": "world map, city map, read a map",
    "synonyms": "",
    "antonyms": "",
    "image_search_query": "colorful world map on white background",
    "image_context": "A colorful world map spread out on a white table showing all continents and oceans",
    "image_tags": "map,world,countries,geography,travel",
    "example_1": "I need a map to find the city.",
    "example_1_translation": "Preciso de um mapa para encontrar a cidade.",
    "example_2": "The map is on the wall.",
    "example_2_translation": "O mapa está na parede.",
    "example_3": "Can you read a map?",
    "example_3_translation": "Você sabe ler um mapa?",
    "pronunciation_tips": "Rhymes with 'cap' and 'tap'",
    "memory_hook": "A map helps you 'map' out your route",
    "related_words": "country, city, travel, direction",
    "common_mistakes": "'Map' not 'mapp' - single 'p'",
    "learning_priority": "high"
  },
  {
    "word": "ticket",
    "phonetic": "/ˈtɪk.ɪt/",
    "part_of_speech": "noun",
    "cefr_level": "A1",
    "category": "Things",
    "subcategory": "Travel",
    "article": "a",
    "plural_form": "tickets",
    "countability": "C",
    "regional_variant": "Both",
    "frequency_rank": 5,
    "primary_meaning": "a paper that gives you permission to travel",
    "secondary_meaning": "",
    "usage_notes": "Shows you paid for transport or entry",
    "common_collocations": "bus ticket, train ticket, movie ticket",
    "synonyms": "",
    "antonyms": "",
    "image_search_query": "red movie ticket with white text",
    "image_context": "A red movie ticket with white text showing the movie name and seat number",
    "image_tags": "ticket,cinema,admission,paper,seat",
    "example_1": "I bought a ticket for the movie.",
    "example_1_translation": "Eu comprei um ingresso para o filme.",
    "example_2": "The ticket is on the table.",
    "example_2_translation": "O ingresso está na mesa.",
    "example_3": "Show your ticket at the door.",
    "example_3_translation": "Mostre seu ingresso na porta.",
    "pronunciation_tips": "'Tick-et' - two syllables, short 'i' sound",
    "memory_hook": "You 'tick' the ticket when you use it",
    "related_words": "bus, train, plane, pay",
    "common_mistakes": "'Ticket' not 'tiket' - has double 't'",
    "learning_priority": "high"
  },
  {
    "word": "passport",
    "phonetic": "/ˈpɑːs.pɔːt/",
    "part_of_speech": "noun",
    "cefr_level": "A1",
    "category": "Things",
    "subcategory": "Travel",
    "article": "a",
    "plural_form": "passports",
    "countability": "C",
    "regional_variant": "Both",
    "frequency_rank": 6,
    "primary_meaning": "an official document for traveling abroad",
    "secondary_meaning": "",
    "usage_notes": "Required for international travel",
    "common_collocations": "passport photo, renew passport, passport control",
    "synonyms": "",
    "antonyms": "",
    "image_search_query": "blue passport with gold emblem",
    "image_context": "A blue passport with a gold emblem on the cover, open to show the photo page",
    "image_tags": "passport,document,travel,identity,official",
    "example_1": "I need my passport to travel abroad.",
    "example_1_translation": "Preciso do meu passaporte para viajar para o exterior.",
    "example_2": "Where is your passport?",
    "example_2_translation": "Onde está o seu passaporte?",
    "example_3": "The passport is in my bag.",
    "example_3_translation": "O passaporte está na minha bolsa.",
    "pronunciation_tips": "'Pass-port' - two syllables, 'a' sounds like 'ah'",
    "memory_hook": "Your passport 'passes' through port borders",
    "related_words": "travel, country, plane, identity",
    "common_mistakes": "'Passport' not 'pasport' - double 's'",
    "learning_priority": "high"
  },
  {
    "word": "hotel",
    "phonetic": "/həʊˈtel/",
    "part_of_speech": "noun",
    "cefr_level": "A1",
    "category": "Places",
    "subcategory": "Accommodation",
    "article": "a",
    "plural_form": "hotels",
    "countability": "C",
    "regional_variant": "Both",
    "frequency_rank": 7,
    "primary_meaning": "a building where you pay to sleep",
    "secondary_meaning": "",
    "usage_notes": "Provides rooms for travelers",
    "common_collocations": "hotel room, book a hotel, hotel lobby",
    "synonyms": "",
    "antonyms": "",
    "image_search_query": "tall building hotel with lit windows at night",
    "image_context": "A tall modern hotel building with many lit windows at night, and a doorman at the entrance",
    "image_tags": "hotel,building,rooms,travel,accommodation",
    "example_1": "We booked a hotel near the beach.",
    "example_1_translation": "Reservamos um hotel perto da praia.",
    "example_2": "The hotel is very big.",
    "example_2_translation": "O hotel é muito grande.",
    "example_3": "I work at a hotel.",
    "example_3_translation": "Eu trabalho em um hotel.",
    "pronunciation_tips": "'Ho-tel' - two syllables, stress on second",
    "memory_hook": "At a hotel, you 'ho' and 'tel' (hold) your stay",
    "related_words": "room, bed, sleep, travel",
    "common_mistakes": "'Hotel' not 'hotal' - 'e' before 'l'",
    "learning_priority": "high"
  },
  {
    "word": "bathroom",
    "phonetic": "/ˈbɑːθ.ruːm/",
    "part_of_speech": "noun",
    "cefr_level": "A1",
    "category": "Places",
    "subcategory": "Home",
    "article": "a",
    "plural_form": "bathrooms",
    "countability": "C",
    "regional_variant": "Both",
    "frequency_rank": 8,
    "primary_meaning": "a room with a toilet and often a shower",
    "secondary_meaning": "",
    "usage_notes": "Where you go to the toilet or wash",
    "common_collocations": "bathroom door, public bathroom, bathroom sink",
    "synonyms": "toilet, restroom",
    "antonyms": "",
    "image_search_query": "white bathroom with toilet sink and mirror",
    "image_context": "A clean white bathroom with a toilet, sink with mirror, and towel on the rack",
    "image_tags": "bathroom,toilet,sink,mirror,white",
    "example_1": "Where is the bathroom, please?",
    "example_1_translation": "Onde fica o banheiro, por favor?",
    "example_2": "The bathroom is on the left.",
    "example_2_translation": "O banheiro fica à esquerda.",
    "example_3": "I need to use the bathroom.",
    "example_3_translation": "Preciso usar o banheiro.",
    "pronunciation_tips": "'Bath-room' - two syllables, 'th' sound clear",
    "memory_hook": "A 'bath' room for washing",
    "related_words": "toilet, shower, water, wash",
    "common_mistakes": "'Bathroom' not 'bathrom' - pronounce the full word",
    "learning_priority": "high"
  },
  {
    "word": "kitchen",
    "phonetic": "/ˈkɪtʃ.ɪn/",
    "part_of_speech": "noun",
    "cefr_level": "A1",
    "category": "Places",
    "subcategory": "Home",
    "article": "a",
    "plural_form": "kitchens",
    "countability": "C",
    "regional_variant": "Both",
    "frequency_rank": 9,
    "primary_meaning": "a room where you cook food",
    "secondary_meaning": "",
    "usage_notes": "Has stove, oven, and often a fridge",
    "common_collocations": "kitchen table, kitchen door, modern kitchen",
    "synonyms": "",
    "antonyms": "",
    "image_search_query": "modern kitchen with white cabinets and stove",
    "image_context": "A modern kitchen with white cabinets, a silver stove, refrigerator, and counter space",
    "image_tags": "kitchen,cooking,stove, cabinets,home",
    "example_1": "Mother is cooking in the kitchen.",
    "example_1_translation": "A mãe está cozinhando na cozinha.",
    "example_2": "The kitchen is very clean.",
    "example_2_translation": "A cozinha é muito limpa.",
    "example_3": "Please wash the dishes in the kitchen.",
    "example_3_translation": "Por favor, lave a louça na cozinha.",
    "pronunciation_tips": "'Kitch-en' - two syllables, 'ch' sounds like 'ch' in 'church'",
    "memory_hook": "You 'kitchen' your food by cooking it",
    "related_words": "cook, food, stove, eat",
    "common_mistakes": "'Kitchen' not 'kichen' - 't' is essential",
    "learning_priority": "high"
  },
  {
    "word": "living room",
    "phonetic": "/ˈlɪv.ɪŋ ruːm/",
    "part_of_speech": "noun",
    "cefr_level": "A1",
    "category": "Places",
    "subcategory": "Home",
    "article": "a",
    "plural_form": "living rooms",
    "countability": "C",
    "regional_variant": "Both",
    "frequency_rank": 10,
    "primary_meaning": "a room for sitting and relaxing",
    "secondary_meaning": "",
    "usage_notes": "Usually has sofa, TV, and chairs",
    "common_collocations": "living room sofa, living room TV, sit in the living room",
    "synonyms": "lounge, sitting room",
    "antonyms": "",
    "image_search_query": "cozy living room with brown leather sofa and TV",
    "image_context": "A cozy living room with a brown leather sofa, flat screen TV, coffee table, and warm lighting",
    "image_tags": "living room,sofa,Tv,lounge,relax",
    "example_1": "We watch TV in the living room.",
    "example_1_translation": "Assistimos TV na sala de estar.",
    "example_2": "The living room is big.",
    "example_2_translation": "A sala de estar é grande.",
    "example_3": "Please sit in the living room.",
    "example_3_translation": "Por favor, sente-se na sala de estar.",
    "pronunciation_tips": "'Liv-ing room' - three syllables total, stress on 'liv'",
    "memory_hook": "A 'living' room where life happens with family",
    "related_words": "sofa, chair, TV, house",
    "common_mistakes": "'Living room' is two words, not one",
    "learning_priority": "high"
  },
  {
    "word": "bedroom",
    "phonetic": "/ˈbed.ruːm/",
    "part_of_speech": "noun",
    "cefr_level": "A1",
    "category": "Places",
    "subcategory": "Home",
    "article": "a",
    "plural_form": "bedrooms",
    "countability": "C",
    "regional_variant": "Both",
    "frequency_rank": 11,
    "primary_meaning": "a room where you sleep",
    "secondary_meaning": "",
    "usage_notes": "Contains a bed, usually has a closet",
    "common_collocations": "bedroom door, bedroom window, master bedroom",
    "synonyms": "",
    "antonyms": "",
    "image_search_query": "cozy bedroom with blue bed and white pillows",
    "image_context": "A cozy bedroom with a blue double bed, white pillows, wooden nightstand, and curtains",
    "image_tags": "bedroom,bed,pillow,nightstand,window",
    "example_1": "My bedroom is on the second floor.",
    "example_1_translation": "Meu quarto fica no segundo andar.",
    "example_2": "Please clean your bedroom.",
    "example_2_translation": "Por favor, limpe seu quarto.",
    "example_3": "The bedroom has a big window.",
    "example_3_translation": "O quarto tem uma janela grande.",
    "pronunciation_tips": "'Bed-room' - two syllables, short 'e' sound",
    "memory_hook": "A 'bed' room for sleeping",
    "related_words": "bed, sleep, pillow, house",
    "common_mistakes": "'Bedroom' not 'bedrom' - full pronunciation",
    "learning_priority": "high"
  },
  {
    "word": "wall",
    "phonetic": "/wɔːl/",
    "part_of_speech": "noun",
    "cefr_level": "A1",
    "category": "Things",
    "subcategory": "Building",
    "article": "a",
    "plural_form": "walls",
    "countability": "C",
    "regional_variant": "Both",
    "frequency_rank": 12,
    "primary_meaning": "a vertical surface that divides rooms",
    "secondary_meaning": "",
    "usage_notes": "Part of a building's structure",
    "common_collocations": "wall clock, wall paper, hang on the wall",
    "synonyms": "",
    "antonyms": "floor",
    "image_search_query": "white wall with picture frame and clock",
    "image_context": "A clean white wall in a room with a picture frame, a round clock, and a shelf",
    "image_tags": "wall,surface,room,building,frame",
    "example_1": "The picture is on the wall.",
    "example_1_translation": "A foto está na parede.",
    "example_2": "The wall is very tall.",
    "example_2_translation": "A parede é muito alta.",
    "example_3": "Please write your name on the wall.",
    "example_3_translation": "Por favor, escreva seu nome na parede.",
    "pronunciation_tips": "Rhymes with 'ball' and 'fall'",
    "memory_hook": "Walls 'wall' off rooms from each other",
    "related_words": "door, window, floor, house",
    "common_mistakes": "'Wall' not 'wawl' - 'a' sound like 'aw'",
    "learning_priority": "high"
  },
  {
    "word": "name",
    "phonetic": "/neɪm/",
    "part_of_speech": "noun",
    "cefr_level": "A1",
    "category": "People",
    "subcategory": "Identity",
    "article": "a",
    "plural_form": "names",
    "countability": "C",
    "regional_variant": "Both",
    "frequency_rank": 13,
    "primary_meaning": "what a person or thing is called",
    "secondary_meaning": "to give a name to someone",
    "usage_notes": "Every person and thing has a name",
    "common_collocations": "first name, last name, my name is",
    "synonyms": "",
    "antonyms": "",
    "image_search_query": "person writing their name on paper",
    "image_context": "A hand writing the name 'John Smith' on a white piece of paper with a blue pen",
    "image_tags": "name,write,paper,identity,signature",
    "example_1": "What is your name?",
    "example_1_translation": "Qual é o seu nome?",
    "example_2": "My name is Maria.",
    "example_2_translation": "Meu nome é Maria.",
    "example_3": "The name of this city is London.",
    "example_3_translation": "O nome desta cidade é Londres.",
    "pronunciation_tips": "Rhymes with 'game' and 'same'",
    "memory_hook": "You 'name' things to call them by",
    "related_words": "person, call, identity, word",
    "common_mistakes": "'Name' not 'naim' - 'a' sounds like 'ay'",
    "learning_priority": "high"
  },
  {
    "word": "birthday",
    "phonetic": "/ˈbɜːθ.deɪ/",
    "part_of_speech": "noun",
    "cefr_level": "A1",
    "category": "Time",
    "subcategory": "Celebration",
    "article": "a",
    "plural_form": "birthdays",
    "countability": "C",
    "regional_variant": "Both",
    "frequency_rank": 14,
    "primary_meaning": "the day you were born",
    "secondary_meaning": "",
    "usage_notes": "Celebrated once a year",
    "common_collocations": "happy birthday, birthday party, birthday cake",
    "synonyms": "",
    "antonyms": "",
    "image_search_query": "birthday cake with candles and colorful decorations",
    "image_context": "A chocolate birthday cake with 18 lit candles, surrounded by colorful balloons and presents",
    "image_tags": "birthday,cake,candles,balloons,celebration",
    "example_1": "When is your birthday?",
    "example_1_translation": "Quando é o seu aniversário?",
    "example_2": "Today is my birthday!",
    "example_2_translation": "Hoje é meu aniversário!",
    "example_3": "We had a birthday party.",
    "example_3_translation": "Tivemos uma festa de aniversário.",
    "pronunciation_tips": "'Birth-day' - two syllables, 'th' sound clear",
    "memory_hook": "The 'birth' day you came into the world",
    "related_words": "party, cake, celebrate, year",
    "common_mistakes": "'Birthday' not 'burthday' - 'i' sound is short",
    "learning_priority": "high"
  },
  {
    "word": "email",
    "phonetic": "/ˈiː.meɪl/",
    "part_of_speech": "noun",
    "cefr_level": "A1",
    "category": "Communication",
    "subcategory": "Technology",
    "article": "an",
    "plural_form": "emails",
    "countability": "C",
    "regional_variant": "Both",
    "frequency_rank": 15,
    "primary_meaning": "a message sent by computer",
    "secondary_meaning": "to send a message by computer",
    "usage_notes": "Electronic mail",
    "common_collocations": "send an email, email address, check email",
    "synonyms": "e-mail, electronic mail",
    "antonyms": "",
    "image_search_query": "computer screen showing email inbox",
    "image_context": "A computer screen showing an email inbox with unread messages in the inbox folder",
    "image_tags": "email,computer,message,inbox,technology",
    "example_1": "I sent you an email.",
    "example_1_translation": "Eu te enviei um e-mail.",
    "example_2": "What is your email address?",
    "example_2_translation": "Qual é o seu endereço de e-mail?",
    "example_3": "Please check your email.",
    "example_3_translation": "Por favor, verifique seu e-mail.",
    "pronunciation_tips": "'E-mail' - two syllables, short 'e' sound",
    "memory_hook": "E-mail 'e'lectronically mails messages",
    "related_words": "computer, message, internet, send",
    "common_mistakes": "'Email' can be written as 'e-mail' or 'email'",
    "learning_priority": "high"
  },
  {
    "word": "website",
    "phonetic": "/ˈweb.saɪt/",
    "part_of_speech": "noun",
    "cefr_level": "A1",
    "category": "Communication",
    "subcategory": "Technology",
    "article": "a",
    "plural_form": "websites",
    "countability": "C",
    "regional_variant": "Both",
    "frequency_rank": 16,
    "primary_meaning": "a place on the internet with information",
    "secondary_meaning": "",
    "usage_notes": "Has a web address like www.example.com",
    "common_collocations": "visit a website, website address, design a website",
    "synonyms": "site, webpage",
    "antonyms": "",
    "image_search_query": "laptop screen showing colorful website homepage",
    "image_context": "A laptop screen displaying a colorful website homepage with images and text",
    "image_tags": "website,internet,laptop,page,online",
    "example_1": "I found this on a website.",
    "example_1_translation": "Eu encontrei isso em um site.",
    "example_2": "What is the website address?",
    "example_2_translation": "Qual é o endereço do site?",
    "example_3": "This website is very good.",
    "example_3_translation": "Este site é muito bom.",
    "pronunciation_tips": "'Web-site' - two syllables, 'site' rhymes with 'light'",
    "memory_hook": "A site on the web - a website",
    "related_words": "internet, computer, page, online",
    "common_mistakes": "'Website' not 'websight' - spelled with 'site'",
    "learning_priority": "high"
  },
  {
    "word": "screen",
    "phonetic": "/skriːn/",
    "part_of_speech": "noun",
    "cefr_level": "A1",
    "category": "Things",
    "subcategory": "Technology",
    "article": "a",
    "plural_form": "screens",
    "countability": "C",
    "regional_variant": "Both",
    "frequency_rank": 17,
    "primary_meaning": "the flat part of a TV or computer",
    "secondary_meaning": "",
    "usage_notes": "Where you see pictures and text",
    "common_collocations": "TV screen, computer screen, flat screen",
    "synonyms": "monitor, display",
    "antonyms": "",
    "image_search_query": "large flat screen TV showing colorful image",
    "image_context": "A large flat screen TV mounted on a wall showing a colorful nature documentary",
    "image_tags": "screen,TV,monitor,display,flat",
    "example_1": "The screen is too small.",
    "example_1_translation": "A tela é pequena demais.",
    "example_2": "Please clean the screen.",
    "example_2_translation": "Por favor, limpe a tela.",
    "example_3": "I watch movies on the screen.",
    "example_3_translation": "Eu assisto filmes na tela.",
    "pronunciation_tips": "Rhymes with 'green' and 'scene'",
    "memory_hook": "The screen 'screens' images for you to see",
    "related_words": "TV, computer, phone, picture",
    "common_mistakes": "'Screen' not 'screan' - 'ee' sound",
    "learning_priority": "high"
  },
  {
    "word": "keyboard",
    "phonetic": "/ˈkiː.bɔːd/",
    "part_of_speech": "noun",
    "cefr_level": "A1",
    "category": "Things",
    "subcategory": "Technology",
    "article": "a",
    "plural_form": "keyboards",
    "countability": "C",
    "regional_variant": "Both",
    "frequency_rank": 18,
    "primary_meaning": "a set of keys for typing on a computer",
    "secondary_meaning": "",
    "usage_notes": "Has letters, numbers, and symbols",
    "common_collocations": "computer keyboard, keyboard shortcut, type on keyboard",
    "synonyms": "",
    "antonyms": "",
    "image_search_query": "black computer keyboard with white keys",
    "image_context": "A black computer keyboard with white letter keys and a numeric keypad on the right",
    "image_tags": "keyboard,computer,keys,typing,technology",
    "example_1": "I type on the keyboard every day.",
    "example_1_translation": "Eu digito no teclado todos os dias.",
    "example_2": "The keyboard has many keys.",
    "example_2_translation": "O teclado tem muitas teclas.",
    "example_3": "Please clean the keyboard.",
    "example_3_translation": "Por favor, limpe o teclado.",
    "pronunciation_tips": "'Key-board' - two syllables, 'key' sounds like 'kee'",
    "memory_hook": "Keys on a board - a keyboard",
    "related_words": "computer, type, key, mouse",
    "common_mistakes": "'Keyboard' not 'keyborad' - check spelling",
    "learning_priority": "high"
  },
  {
    "word": "mouse",
    "phonetic": "/maʊs/",
    "part_of_speech": "noun",
    "cefr_level": "A1",
    "category": "Things",
    "subcategory": "Technology",
    "article": "a",
    "plural_form": "mice",
    "countability": "C",
    "regional_variant": "Both",
    "frequency_rank": 19,
    "primary_meaning": "a small animal or a computer device",
    "secondary_meaning": "",
    "usage_notes": "Computer mouse moves the cursor",
    "common_collocations": "computer mouse, wireless mouse, click the mouse",
    "synonyms": "",
    "antonyms": "",
    "image_search_query": "black computer mouse on white desk mat",
    "image_context": "A black computer mouse on a white desk mat next to a keyboard and coffee cup",
    "image_tags": "mouse,computer,click,desk,technology",
    "example_1": "Move the mouse to click.",
    "example_1_translation": "Mova o mouse para clicar.",
    "example_2": "I need a new mouse for my computer.",
    "example_2_translation": "Preciso de um novo mouse para meu computador.",
    "example_3": "The mouse is on the desk.",
    "example_3_translation": "O mouse está na mesa.",
    "pronunciation_tips": "Rhymes with 'house' and 'mouse' (the animal)",
    "memory_hook": "The mouse 'mouses' around the screen",
    "related_words": "computer, click, screen, cursor",
    "common_mistakes": "Plural is 'mice' for animals, but for computer mouse often 'mouses' is accepted",
    "learning_priority": "high"
  },
  {
    "word": "dinner",
    "phonetic": "/ˈdɪn.ər/",
    "part_of_speech": "noun",
    "cefr_level": "A1",
    "category": "Food",
    "subcategory": "Meals",
    "article": "",
    "plural_form": "",
    "countability": "U",
    "regional_variant": "Both",
    "frequency_rank": 20,
    "primary_meaning": "the main meal of the day, usually in the evening",
    "secondary_meaning": "",
    "usage_notes": "Often eaten between 6pm and 8pm",
    "common_collocations": "have dinner, dinner time, cook dinner",
    "synonyms": "supper",
    "antonyms": "breakfast",
    "image_search_query": "family eating dinner at wooden table with candles",
    "image_context": "A family of four eating dinner at a wooden table with plates of food and lit candles",
    "image_tags": "dinner,family,table,food,eating",
    "example_1": "We have dinner at seven o'clock.",
    "example_1_translation": "Jantamos às sete.",
    "example_2": "Dinner is ready!",
    "example_2_translation": "O jantar está pronto!",
    "example_3": "I cooked dinner for my family.",
    "example_3_translation": "Eu cozinhei o jantar para minha família.",
    "pronunciation_tips": "'Din-ner' - two syllables, short 'i' sound",
    "memory_hook": "Dinner 'dinners' your day with a full meal",
    "related_words": "food, eat, lunch, breakfast",
    "common_mistakes": "'Dinner' not 'diner' - two 'n's",
    "learning_priority": "high"
  },
  {
    "word": "lunch",
    "phonetic": "/lʌntʃ/",
    "part_of_speech": "noun",
    "cefr_level": "A1",
    "category": "Food",
    "subcategory": "Meals",
    "article": "",
    "plural_form": "",
    "countability": "U",
    "regional_variant": "Both",
    "frequency_rank": 21,
    "primary_meaning": "a meal eaten in the middle of the day",
    "secondary_meaning": "",
    "usage_notes": "Usually between 12pm and 2pm",
    "common_collocations": "have lunch, lunch break, pack lunch",
    "synonyms": "",
    "antonyms": "dinner",
    "image_search_query": "person eating lunch at cafe with sandwich and juice",
    "image_context": "A person sitting at a café table eating a sandwich and drinking orange juice for lunch",
    "image_tags": "lunch,sandwich,cafe,meal,midday",
    "example_1": "Let's have lunch together.",
    "example_1_translation": "Vamos almoçar juntos.",
    "example_2": "I eat lunch at noon.",
    "example_2_translation": "Eu almoço ao meio-dia.",
    "example_3": "What do you want for lunch?",
    "example_3_translation": "O que você quer para o almoço?",
    "pronunciation_tips": "Rhymes with 'bunch' and 'punch'",
    "memory_hook": "Lunch 'lunches' your afternoon energy",
    "related_words": "food, eat, dinner, breakfast",
    "common_mistakes": "'Lunch' not 'lunchh' - single 'h'",
    "learning_priority": "high"
  },
  {
    "word": "breakfast",
    "phonetic": "/ˈbrek.fəst/",
    "part_of_speech": "noun",
    "cefr_level": "A1",
    "category": "Food",
    "subcategory": "Meals",
    "article": "",
    "plural_form": "",
    "countability": "U",
    "regional_variant": "Both",
    "frequency_rank": 22,
    "primary_meaning": "the first meal of the day",
    "secondary_meaning": "",
    "usage_notes": "Eaten in the morning after waking",
    "common_collocations": "have breakfast, breakfast time, skip breakfast",
    "synonyms": "",
    "antonyms": "dinner",
    "image_search_query": "breakfast plate with eggs toast and orange juice",
    "image_context": "A breakfast plate with fried eggs, toast with butter, bacon, and a glass of orange juice",
    "image_tags": "breakfast,eggs,toast,juice,morning",
    "example_1": "I have breakfast at seven.",
    "example_1_translation": "Eu tomo café da manhã às sete.",
    "example_2": "Breakfast is the most important meal.",
    "example_2_translation": "Café da manhã é a refeição mais importante.",
    "example_3": "What do you want for breakfast?",
    "example_3_translation": "O que você quer para o café da manhã?",
    "pronunciation_tips": "'Break-fast' - two syllables, 'break' sounds like 'brake'",
    "memory_hook": "You 'break' your 'fast' from not eating while sleeping",
    "related_words": "food, eat, morning, lunch",
    "common_mistakes": "'Breakfast' not 'brekfast' - full pronunciation",
    "learning_priority": "high"
  },
  {
    "word": "doctor",
    "phonetic": "/ˈdɒk.tər/",
    "part_of_speech": "noun",
    "cefr_level": "A1",
    "category": "People",
    "subcategory": "Health",
    "article": "a",
    "plural_form": "doctors",
    "countability": "C",
    "regional_variant": "Both",
    "frequency_rank": 23,
    "primary_meaning": "a person who treats sick people",
    "secondary_meaning": "",
    "usage_notes": "Has medical training",
    "common_collocations": "see a doctor, doctor appointment, doctor says",
    "synonyms": "physician",
    "antonyms": "",
    "image_search_query": "female doctor in white coat with stethoscope",
    "image_context": "A female doctor in a white coat with a stethoscope around her neck, smiling kindly",
    "image_tags": "doctor,medical,white coat,stethoscope,health",
    "example_1": "I need to see a doctor.",
    "example_1_translation": "Preciso consultar um médico.",
    "example_2": "The doctor is very kind.",
    "example_2_translation": "O médico é muito gentil.",
    "example_3": "My mother is a doctor.",
    "example_3_translation": "Minha mãe é médica.",
    "pronunciation_tips": "'Doc-tor' - two syllables, 'c' sounds like 'k'",
    "memory_hook": "A doctor 'doctors' you back to health",
    "related_words": "hospital, medicine, nurse, sick",
    "common_mistakes": "'Doctor' not 'doktor' - 'c' is soft in this word",
    "learning_priority": "high"
  },
  {
    "word": "rain",
    "phonetic": "/reɪn/",
    "part_of_speech": "noun",
    "cefr_level": "A1",
    "category": "Nature",
    "subcategory": "Weather",
    "article": "",
    "plural_form": "",
    "countability": "U",
    "regional_variant": "Both",
    "frequency_rank": 24,
    "primary_meaning": "water that falls from clouds",
    "secondary_meaning": "to fall from clouds",
    "usage_notes": "Opposite of sunny weather",
    "common_collocations": "heavy rain, rain drops, it's raining",
    "synonyms": "",
    "antonyms": "sunshine",
    "image_search_query": "dark clouds with rain falling over city",
    "image_context": "Dark grey clouds with rain falling over a city street, people with umbrellas walking by",
    "image_tags": "rain,clouds,water,weather,wet",
    "example_1": "It is raining outside.",
    "example_1_translation": "Está chovendo lá fora.",
    "example_2": "I don't like rain.",
    "example_2_translation": "Eu não gosto de chuva.",
    "example_3": "The rain is very heavy.",
    "example_3_translation": "A chuva é muito forte.",
    "pronunciation_tips": "Rhymes with 'train' and 'pain'",
    "memory_hook": "Rain 'rains' down from the sky",
    "related_words": "cloud, water, weather, wet",
    "common_mistakes": "'Rain' not 'rein' - 'ai' sound",
    "learning_priority": "high"
  },
  {
    "word": "dog",
    "phonetic": "/dɒɡ/",
    "part_of_speech": "noun",
    "cefr_level": "A1",
    "category": "Animals",
    "subcategory": "Pets",
    "article": "a",
    "plural_form": "dogs",
    "countability": "C",
    "regional_variant": "Both",
    "frequency_rank": 25,
    "primary_meaning": "a common domestic animal with four legs",
    "secondary_meaning": "",
    "usage_notes": "Often kept as a pet",
    "common_collocations": "pet dog, stray dog, dog bark",
    "synonyms": "puppy",
    "antonyms": "",
    "image_search_query": "brown dog sitting and smiling at camera",
    "image_context": "A friendly brown dog sitting on a green grass lawn looking at the camera with tongue out",
    "image_tags": "dog,brown,pet,grass,four legs",
    "example_1": "I have a dog at home.",
    "example_1_translation": "Eu tenho um cachorro em casa.",
    "example_2": "The dog is very cute.",
    "example_2_translation": "O cachorro é muito fofo.",
    "example_3": "My dog likes to play.",
    "example_3_translation": "Meu cachorro gosta de brincar.",
    "pronunciation_tips": "Rhymes with 'log' and 'frog'",
    "memory_hook": "Dogs 'dog' after their owners everywhere",
    "related_words": "cat, pet, animal, bark",
    "common_mistakes": "'Dog' not 'dawg' - proper spelling",
    "learning_priority": "high"
  }
]
